{
  "coord": {
    "lon": 72.8333,
    "lat": 21.1667
  },
  "weather": [
    {
      "id": 804,
      "main": "Clouds",
      "description": "overcast clouds",
      "icon": "04d"
    }
  ],
  "base": "stations",
  "main": {
    "temp": 26.96,
    "feels_like": 26.99,
    "temp_min": 26.96,
    "temp_max": 26.96,
    "pressure": 1012,
    "humidity": 43,
    "sea_level": 1012,
    "grnd_level": 1011
  },
  "visibility": 10000,
  "wind": {
    "speed": 2.75,
    "deg": 8,
    "gust": 5.38
  },
  "clouds": {
    "all": 100
  },
  "dt": 1774232996,
  "sys": {
    "country": "IN",
    "sunrise": 1774228220,
    "sunset": 1774272017
  },
  "timezone": 19800,
  "id": 1255364,
  "name": "Surat",
  "cod": 200,
  "_last_updated_utc": "2026-03-23T02:29:56.153Z"
}