{
  "coord": {
    "lon": 72.8333,
    "lat": 21.1667
  },
  "weather": [
    {
      "id": 803,
      "main": "Clouds",
      "description": "broken clouds",
      "icon": "04n"
    }
  ],
  "base": "stations",
  "main": {
    "temp": 28.15,
    "feels_like": 27.12,
    "temp_min": 28.15,
    "temp_max": 28.15,
    "pressure": 1012,
    "humidity": 28,
    "sea_level": 1012,
    "grnd_level": 1010
  },
  "visibility": 10000,
  "wind": {
    "speed": 3.03,
    "deg": 339,
    "gust": 5.12
  },
  "clouds": {
    "all": 76
  },
  "dt": 1774110773,
  "sys": {
    "country": "IN",
    "sunrise": 1774055531,
    "sunset": 1774099181
  },
  "timezone": 19800,
  "id": 1255364,
  "name": "Surat",
  "cod": 200,
  "_last_updated_utc": "2026-03-21T16:32:53.951Z"
}