{
  "coord": {
    "lon": 72.8333,
    "lat": 21.1667
  },
  "weather": [
    {
      "id": 800,
      "main": "Clear",
      "description": "clear sky",
      "icon": "01d"
    }
  ],
  "base": "stations",
  "main": {
    "temp": 34.99,
    "feels_like": 36.07,
    "temp_min": 34.99,
    "temp_max": 34.99,
    "pressure": 1008,
    "humidity": 36,
    "sea_level": 1008,
    "grnd_level": 1007
  },
  "visibility": 6000,
  "wind": {
    "speed": 2.06,
    "deg": 50
  },
  "clouds": {
    "all": 8
  },
  "dt": 1774428897,
  "sys": {
    "type": 1,
    "id": 9071,
    "country": "IN",
    "sunrise": 1774400909,
    "sunset": 1774444853
  },
  "timezone": 19800,
  "id": 1255364,
  "name": "Surat",
  "cod": 200,
  "_last_updated_utc": "2026-03-25T08:54:57.232Z"
}