{
  "coord": {
    "lon": 72.8333,
    "lat": 21.1667
  },
  "weather": [
    {
      "id": 500,
      "main": "Rain",
      "description": "light rain",
      "icon": "10n"
    }
  ],
  "base": "stations",
  "main": {
    "temp": 26.69,
    "feels_like": 29.78,
    "temp_min": 26.69,
    "temp_max": 26.69,
    "pressure": 999,
    "humidity": 89,
    "sea_level": 999,
    "grnd_level": 998
  },
  "visibility": 10000,
  "wind": {
    "speed": 9.73,
    "deg": 238,
    "gust": 15.35
  },
  "rain": {
    "1h": 0.95
  },
  "clouds": {
    "all": 100
  },
  "dt": 1784846901,
  "sys": {
    "country": "IN",
    "sunrise": 1784853534,
    "sunset": 1784901066
  },
  "timezone": 19800,
  "id": 1255364,
  "name": "Surat",
  "cod": 200,
  "_last_updated_utc": "2026-07-23T22:57:26.376Z"
}