{
  "coord": {
    "lon": 72.8333,
    "lat": 21.1667
  },
  "weather": [
    {
      "id": 721,
      "main": "Haze",
      "description": "haze",
      "icon": "50d"
    }
  ],
  "base": "stations",
  "main": {
    "temp": 32.99,
    "feels_like": 39.99,
    "temp_min": 32.99,
    "temp_max": 32.99,
    "pressure": 1006,
    "humidity": 66,
    "sea_level": 1006,
    "grnd_level": 1005
  },
  "visibility": 5000,
  "wind": {
    "speed": 6.17,
    "deg": 200
  },
  "clouds": {
    "all": 20
  },
  "dt": 1777271014,
  "sys": {
    "type": 1,
    "id": 9071,
    "country": "IN",
    "sunrise": 1777250448,
    "sunset": 1777296699
  },
  "timezone": 19800,
  "id": 1255364,
  "name": "Surat",
  "cod": 200,
  "_last_updated_utc": "2026-04-27T06:28:15.403Z"
}