{
  "coord": {
    "lon": 72.8333,
    "lat": 21.1667
  },
  "weather": [
    {
      "id": 802,
      "main": "Clouds",
      "description": "scattered clouds",
      "icon": "03n"
    }
  ],
  "base": "stations",
  "main": {
    "temp": 24.29,
    "feels_like": 24.76,
    "temp_min": 24.29,
    "temp_max": 24.29,
    "pressure": 1013,
    "humidity": 76,
    "sea_level": 1013,
    "grnd_level": 1012
  },
  "visibility": 10000,
  "wind": {
    "speed": 11.05,
    "deg": 311,
    "gust": 14.32
  },
  "clouds": {
    "all": 34
  },
  "dt": 1773931621,
  "sys": {
    "country": "IN",
    "sunrise": 1773882841,
    "sunset": 1773926345
  },
  "timezone": 19800,
  "id": 1255364,
  "name": "Surat",
  "cod": 200,
  "_last_updated_utc": "2026-03-19T14:51:17.316Z"
}