{
  "coord": {
    "lon": 72.8333,
    "lat": 21.1667
  },
  "weather": [
    {
      "id": 801,
      "main": "Clouds",
      "description": "few clouds",
      "icon": "02n"
    }
  ],
  "base": "stations",
  "main": {
    "temp": 29.99,
    "feels_like": 30.44,
    "temp_min": 29.99,
    "temp_max": 29.99,
    "pressure": 1009,
    "humidity": 46,
    "sea_level": 1009,
    "grnd_level": 1007
  },
  "visibility": 10000,
  "wind": {
    "speed": 2.11,
    "deg": 247,
    "gust": 4.9
  },
  "clouds": {
    "all": 11
  },
  "dt": 1776616925,
  "sys": {
    "country": "IN",
    "sunrise": 1776559598,
    "sunset": 1776605321
  },
  "timezone": 19800,
  "id": 1255364,
  "name": "Surat",
  "cod": 200,
  "_last_updated_utc": "2026-04-19T16:43:03.805Z"
}